wireui/__init__.py
wireui/__main__.py
wireui/library/__init__.py
wireui/library/config.py
wireui/library/integrity.py
wireui/library/io_.py
wireui/library/keys.py
wireui/library/wireui.py
wireui/library/typedefs/__init__.py
wireui/library/typedefs/dicts.py
wireui/library/typedefs/exceptions.py
wireui/library/typedefs/peers.py
wireui/library/typedefs/settings.py
wireui/library/typedefs/sites.py
wireui/library/typedefs/tables.py
wireui/library/typedefs/test_tables.py
wireui/ui/__init__.py
wireui/ui/console.py
wireui/ui/menus.py
wireui/ui/peers.py
wireui/ui/shared.py
wireui/ui/sites.py
wireui/ui/strings.py
wireui/ui/ui.py
wireui_TheTimmoth-0.1.0a6.dist-info/LICENSE
wireui_TheTimmoth-0.1.0a6.dist-info/METADATA
wireui_TheTimmoth-0.1.0a6.dist-info/WHEEL
wireui_TheTimmoth-0.1.0a6.dist-info/top_level.txt
wireui_TheTimmoth-0.1.0a6.dist-info/RECORD
