Metadata-Version: 2.1
Name: wireui-TheTimmoth
Version: 0.1.0a6
Summary: A tool for creating and managing wireguard configs
Home-page: https://github.com/TheTimmoth/wireui
Author: Tim Schlottmann
Author-email: coding@timsc.de
License: UNKNOWN
Keywords: wireguard,wireui
Platform: Linux
Platform: Windows
Classifier: Programming Language :: Python :: 3.6
Classifier: License :: OSI Approved :: MIT License
Classifier: Operating System :: POSIX :: Linux
Classifier: Operating System :: Microsoft :: Windows
Classifier: Development Status :: 3 - Alpha
Classifier: Environment :: Console
Requires-Python: >=3.6
